semantic_search_mcp/__init__.py
semantic_search_mcp/chunker.py
semantic_search_mcp/cli.py
semantic_search_mcp/config.py
semantic_search_mcp/database.py
semantic_search_mcp/embedder.py
semantic_search_mcp/gitignore.py
semantic_search_mcp/indexer.py
semantic_search_mcp/searcher.py
semantic_search_mcp/server.py
semantic_search_mcp/watcher.py
semantic_search_mcp/commands/semantic-search-cancel.md
semantic_search_mcp/commands/semantic-search-clear.md
semantic_search_mcp/commands/semantic-search-pause.md
semantic_search_mcp/commands/semantic-search-reindex.md
semantic_search_mcp/commands/semantic-search-resume.md
semantic_search_mcp/commands/semantic-search-search.md
semantic_search_mcp/commands/semantic-search-status.md
semantic_search_mcp/skills/semantic-search:cancel/SKILL.md
semantic_search_mcp/skills/semantic-search:clear/SKILL.md
semantic_search_mcp/skills/semantic-search:pause/SKILL.md
semantic_search_mcp/skills/semantic-search:reindex/SKILL.md
semantic_search_mcp/skills/semantic-search:resume/SKILL.md
semantic_search_mcp/skills/semantic-search:search/SKILL.md
semantic_search_mcp/skills/semantic-search:status/SKILL.md
semantic_search_mcp-0.3.0.dist-info/METADATA
semantic_search_mcp-0.3.0.dist-info/WHEEL
semantic_search_mcp-0.3.0.dist-info/entry_points.txt
semantic_search_mcp-0.3.0.dist-info/licenses/LICENSE
semantic_search_mcp-0.3.0.dist-info/RECORD
