Metadata-Version: 2.4
Name: semantic-search-mcp
Version: 0.3.0
Summary: MCP server for semantic code search using local embeddings
Project-URL: Homepage, https://github.com/adam-hanna/semantic-search-mcp
Project-URL: Repository, https://github.com/adam-hanna/semantic-search-mcp
Project-URL: Issues, https://github.com/adam-hanna/semantic-search-mcp/issues
Author-email: Adam Hanna <adamhanna@gmail.com>
License-Expression: MIT
License-File: LICENSE
Keywords: ai,claude,code-search,embeddings,llm,mcp,semantic-search
Classifier: Development Status :: 4 - Beta
Classifier: Intended Audience :: Developers
Classifier: License :: OSI Approved :: MIT License
Classifier: Programming Language :: Python :: 3
Classifier: Programming Language :: Python :: 3.11
Classifier: Programming Language :: Python :: 3.12
Classifier: Programming Language :: Python :: 3.13
Classifier: Topic :: Software Development :: Libraries :: Python Modules
Classifier: Topic :: Text Processing :: Indexing
Requires-Python: <3.14,>=3.11
Requires-Dist: apsw>=3.45.0
Requires-Dist: fastembed>=0.4.0
Requires-Dist: mcp[cli]>=1.0.0
Requires-Dist: onnx>=1.15.0
Requires-Dist: pathspec>=0.12.0
Requires-Dist: pydantic>=2.0.0
Requires-Dist: sqlite-vec>=0.1.6
Requires-Dist: tree-sitter-language-pack>=0.4.0
Requires-Dist: watchfiles>=1.0.0
Provides-Extra: dev
Requires-Dist: pytest-asyncio>=0.24.0; extra == 'dev'
Requires-Dist: pytest-cov>=6.0.0; extra == 'dev'
Requires-Dist: pytest>=8.0.0; extra == 'dev'
Provides-Extra: gpu
Requires-Dist: onnxruntime-gpu>=1.17.0; extra == 'gpu'
Provides-Extra: unixcoder
Requires-Dist: torch>=2.0.0; extra == 'unixcoder'
Requires-Dist: transformers>=4.30.0; extra == 'unixcoder'
